akitools/__init__.py
akitools/tools.py
akitools/vk.py
akitools-0.2.7.dist-info/LICENSE
akitools-0.2.7.dist-info/METADATA
akitools-0.2.7.dist-info/WHEEL
akitools-0.2.7.dist-info/top_level.txt
akitools-0.2.7.dist-info/RECORD
