Metadata-Version: 2.1
Name: akitools
Version: 0.2.7
Summary: akitools
Home-page: https://github.com/aki/akitools
Author: aki
Author-email: heti@qq.com
License: BSD
Platform: UNKNOWN
Classifier: Programming Language :: Python :: 3
Classifier: Operating System :: OS Independent
Requires-Dist: requests
